dfa_mutate/__init__.py
dfa_mutate-0.1.3.dist-info/LICENSE
dfa_mutate-0.1.3.dist-info/METADATA
dfa_mutate-0.1.3.dist-info/WHEEL
dfa_mutate-0.1.3.dist-info/RECORD
