Metadata-Version: 2.1
Name: dfa-mutate
Version: 0.1.3
Summary: Library for mutating a DFA represented using the dfa library.
Home-page: https://github.com/mvcisback/dfa-mutate
License: MIT
Author: Marcell Vazquez-Chanlatte
Author-email: mvc@linux.com
Requires-Python: >=3.9,<4.0
Classifier: License :: OSI Approved :: MIT License
Classifier: Programming Language :: Python :: 3
Classifier: Programming Language :: Python :: 3.9
Classifier: Programming Language :: Python :: 3.10
Classifier: Programming Language :: Python :: 3.11
Requires-Dist: dfa (>=4.6.3,<5.0.0)
Requires-Dist: numpy (>=1.24.3,<2.0.0)
Project-URL: Repository, https://github.com/mvcisback/dfa-mutate
